{
  "projects": [
    {
      "id": "0c6b",
      "title": "Project 3",
      "detail": "Project Detail 3",
      "complete": false
    },
    {
      "id": "eda4",
      "title": "Project 3",
      "detail": "Project Detail 3",
      "complete": false
    },
    {
      "id": "0f37",
      "title": "Project 4",
      "detail": "Project Detail 4",
      "complete": false
    },
    {
      "id": "5dcb",
      "title": "Project 5",
      "detail": "Project Detail 5",
      "complete": false
    },
    {
      "id": "7545",
      "title": "Project 6",
      "detail": "Project Detail 6",
      "complete": false
    }
  ]
}